odoo/addons/stock_buffer_sales_analysis/README.rst
odoo/addons/stock_buffer_sales_analysis/__init__.py
odoo/addons/stock_buffer_sales_analysis/__manifest__.py
odoo/addons/stock_buffer_sales_analysis/i18n/es.po
odoo/addons/stock_buffer_sales_analysis/i18n/it.po
odoo/addons/stock_buffer_sales_analysis/i18n/pt_BR.po
odoo/addons/stock_buffer_sales_analysis/i18n/stock_buffer_sales_analysis.pot
odoo/addons/stock_buffer_sales_analysis/models/__init__.py
odoo/addons/stock_buffer_sales_analysis/models/stock_buffer.py
odoo/addons/stock_buffer_sales_analysis/readme/CONTRIBUTORS.md
odoo/addons/stock_buffer_sales_analysis/readme/CREDITS.md
odoo/addons/stock_buffer_sales_analysis/readme/DESCRIPTION.md
odoo/addons/stock_buffer_sales_analysis/static/description/icon.png
odoo/addons/stock_buffer_sales_analysis/static/description/index.html
odoo/addons/stock_buffer_sales_analysis/views/stock_buffer_views.xml
odoo_addon_stock_buffer_sales_analysis-18.0.1.0.0.2.dist-info/METADATA
odoo_addon_stock_buffer_sales_analysis-18.0.1.0.0.2.dist-info/WHEEL
odoo_addon_stock_buffer_sales_analysis-18.0.1.0.0.2.dist-info/top_level.txt
odoo_addon_stock_buffer_sales_analysis-18.0.1.0.0.2.dist-info/RECORD
